staticmapgenerator/__init__.py
staticmapgenerator/map.py
staticmapgenerator-1.0.0.dist-info/LICENSE.md
staticmapgenerator-1.0.0.dist-info/WHEEL
staticmapgenerator-1.0.0.dist-info/METADATA
staticmapgenerator-1.0.0.dist-info/RECORD
