Metadata-Version: 2.1
Name: staticmapgenerator
Version: 1.0.0
Summary: Module generating images of maps by coordinates
Home-page: https://github.com/D1ffic00lt/map-generator-python
License: MIT
Author: D1ffic00lt
Author-email: dm.filinov@gmail.com
Requires-Python: >=3.8,<4.0
Classifier: License :: OSI Approved :: MIT License
Classifier: Programming Language :: Python :: 3
Classifier: Programming Language :: Python :: 3.8
Classifier: Programming Language :: Python :: 3.9
Classifier: Programming Language :: Python :: 3.10
Classifier: Programming Language :: Python :: 3.11
Project-URL: Documentation, https://github.com/D1ffic00lt/map-generator-python/blob/main/README.md
Project-URL: Repository, https://github.com/D1ffic00lt/map-generator-python
